time_execution/__init__.py
time_execution/decorator.py
time_execution/py.typed
time_execution/timed.py
time_execution/backends/__init__.py
time_execution/backends/base.py
time_execution/backends/elasticsearch.py
time_execution/backends/threaded.py
timeexecution-8.4.1.dist-info/licenses/LICENSE
timeexecution-8.4.1.dist-info/METADATA
timeexecution-8.4.1.dist-info/WHEEL
timeexecution-8.4.1.dist-info/top_level.txt
timeexecution-8.4.1.dist-info/RECORD
