Metadata-Version: 2.4
Name: timeexecution
Version: 8.4.1
Summary: Python project
Home-page: https://github.com/kpn/py-timeexecution
Author: KPN DE Platform
Author-email: de-platform@kpn.com
Classifier: Development Status :: 5 - Production/Stable
Classifier: Environment :: Web Environment
Classifier: Intended Audience :: Developers
Classifier: Operating System :: OS Independent
Classifier: License :: OSI Approved :: Apache Software License
Classifier: Programming Language :: Python
Classifier: Programming Language :: Python :: 3
Classifier: Programming Language :: Python :: 3.9
Classifier: Programming Language :: Python :: 3.10
Classifier: Programming Language :: Python :: 3.11
Classifier: Programming Language :: Python :: 3.12
Classifier: Programming Language :: Python :: 3.13
Classifier: Topic :: Internet :: WWW/HTTP
Classifier: Topic :: Software Development :: Libraries :: Python Modules
License-File: LICENSE
Requires-Dist: pkgsettings>=0.9.2
Requires-Dist: fqn-decorators<3.0.0,>=1.2.5
Requires-Dist: typing-extensions<5.0.0,>=4.5.0
Provides-Extra: all
Requires-Dist: elasticsearch<10.0.0,>=8.0.0; extra == "all"
Provides-Extra: elasticsearch
Requires-Dist: elasticsearch<10.0.0,>=8.0.0; extra == "elasticsearch"
Dynamic: author
Dynamic: author-email
Dynamic: classifier
Dynamic: description
Dynamic: description-content-type
Dynamic: home-page
Dynamic: license-file
Dynamic: provides-extra
Dynamic: requires-dist
Dynamic: summary
